Workbook

Sheet Сводка по странам
A1: № | B1: Страна | C1: Блок | D1: Формулировка на упаковке | E1: Использование заявки «без пальмового масла» | F1: Норм всего (вкл. блок) | G1: Действуют | H1: Вступают позже | I1: Предложения | J1: Регулирование кратко | K1: Рыночная практика заявки | L1: Код | M1: Код блока
A2: 1 | B2: Польша | C2: ЕС | D2: bez oleju palmowego | E2: Высокая | F2: =COUNTIF(Меры!$B$2:$B$26,L2)+COUNTIF(Меры!$B$2:$B$26,M2) -> 5 | G2: =COUNTIFS(Меры!$B$2:$B$26,L2,Меры!$E$2:$E$26,"Действует")+COUNTIFS(Меры!$B$2:$B$26,M2,Меры!$E$2:$E$26,"Действует") -> 3 | H2: =COUNTIFS(Меры!$B$2:$B$26,L2,Меры!$E$2:$E$26,"Принято, вступает позже")+COUNTIFS(Меры!$B$2:$B$26,M2,Меры!$E$2:$E$26,"Принято, вступает позже") -> 1 | I2: =COUNTIFS(Меры!$B$2:$B$26,L2,Меры!$E$2:$E$26,"Предложение / проект")+COUNTIFS(Меры!$B$2:$B$26,M2,Меры!$E$2:$E$26,"Предложение / проект") -> 1 | J2: Национальных норм о пальмовом масле нет; действуют общие правила ЕС. | K2: Żabka: 100% собственных марок без пальмового масла, в брендах поставщиков — только RSPO. Заявка на снеках, пастах, детских смесях, B2B-маргаринах. | L2: PL | M2: EU
A3: 2 | B3: Чехия | C3: ЕС | D3: bez palmového oleje | E3: Высокая | F3: =COUNTIF(Меры!$B$2:$B$26,L3)+COUNTIF(Меры!$B$2:$B$26,M3) -> 5 | G3: =COUNTIFS(Меры!$B$2:$B$26,L3,Меры!$E$2:$E$26,"Действует")+COUNTIFS(Меры!$B$2:$B$26,M3,Меры!$E$2:$E$26,"Действует") -> 3 | H3: =COUNTIFS(Меры!$B$2:$B$26,L3,Меры!$E$2:$E$26,"Принято, вступает позже")+COUNTIFS(Меры!$B$2:$B$26,M3,Меры!$E$2:$E$26,"Принято, вступает позже") -> 1 | I3: =COUNTIFS(Меры!$B$2:$B$26,L3,Меры!$E$2:$E$26,"Предложение / проект")+COUNTIFS(Меры!$B$2:$B$26,M3,Меры!$E$2:$E$26,"Предложение / проект") -> 1 | J3: Национальных норм о пальмовом масле нет; действуют общие правила ЕС. | K3: Заявка в названиях товаров онлайн-ритейла (Rohlik: Lef, Chocoland). Родина «Дня без пальмового масла» (1 февраля). | L3: CZ | M3: EU
A4: 3 | B4: Словакия | C4: ЕС | D4: bez palmového oleja | E4: Средняя | F4: =COUNTIF(Меры!$B$2:$B$26,L4)+COUNTIF(Меры!$B$2:$B$26,M4) -> 5 | G4: =COUNTIFS(Меры!$B$2:$B$26,L4,Меры!$E$2:$E$26,"Действует")+COUNTIFS(Меры!$B$2:$B$26,M4,Меры!$E$2:$E$26,"Действует") -> 3 | H4: =COUNTIFS(Меры!$B$2:$B$26,L4,Меры!$E$2:$E$26,"Принято, вступает позже")+COUNTIFS(Меры!$B$2:$B$26,M4,Меры!$E$2:$E$26,"Принято, вступает позже") -> 1 | I4: =COUNTIFS(Меры!$B$2:$B$26,L4,Меры!$E$2:$E$26,"Предложение / проект")+COUNTIFS(Меры!$B$2:$B$26,M4,Меры!$E$2:$E$26,"Предложение / проект") -> 1 | J4: Национальных норм о пальмовом масле нет; общие правила ЕС, включая запрет «двойного качества». | K4: Локальные бренды ореховых паст; тема «двойного качества» (пальмовое масло вместо масла в рецептурах для Востока). | L4: SK | M4: EU
A5: 4 | B5: Венгрия | C5: ЕС | D5: pálmaolaj-mentes | E5: Низкая | F5: =COUNTIF(Меры!$B$2:$B$26,L5)+COUNTIF(Меры!$B$2:$B$26,M5) -> 5 | G5: =COUNTIFS(Меры!$B$2:$B$26,L5,Меры!$E$2:$E$26,"Действует")+COUNTIFS(Меры!$B$2:$B$26,M5,Меры!$E$2:$E$26,"Действует") -> 3 | H5: =COUNTIFS(Меры!$B$2:$B$26,L5,Меры!$E$2:$E$26,"Принято, вступает позже")+COUNTIFS(Меры!$B$2:$B$26,M5,Меры!$E$2:$E$26,"Принято, вступает позже") -> 1 | I5: =COUNTIFS(Меры!$B$2:$B$26,L5,Меры!$E$2:$E$26,"Предложение / проект")+COUNTIFS(Меры!$B$2:$B$26,M5,Меры!$E$2:$E$26,"Предложение / проект") -> 1 | J5: Национальных норм о пальмовом масле не выявлено; действуют общие правила ЕС. | K5: Ниша free-from; в СМИ тема звучит через цены и EUDR. | L5: HU | M5: EU
A6: 5 | B6: Румыния | C6: ЕС | D6: fără ulei de palmier | E6: Средняя | F6: =COUNTIF(Меры!$B$2:$B$26,L6)+COUNTIF(Меры!$B$2:$B$26,M6) -> 5 | G6: =COUNTIFS(Меры!$B$2:$B$26,L6,Меры!$E$2:$E$26,"Действует")+COUNTIFS(Меры!$B$2:$B$26,M6,Меры!$E$2:$E$26,"Действует") -> 3 | H6: =COUNTIFS(Меры!$B$2:$B$26,L6,Меры!$E$2:$E$26,"Принято, вступает позже")+COUNTIFS(Меры!$B$2:$B$26,M6,Меры!$E$2:$E$26,"Принято, вступает позже") -> 1 | I6: =COUNTIFS(Меры!$B$2:$B$26,L6,Меры!$E$2:$E$26,"Предложение / проект")+COUNTIFS(Меры!$B$2:$B$26,M6,Меры!$E$2:$E$26,"Предложение / проект") -> 1 | J6: Национальных норм о пальмовом масле не выявлено; действуют общие правила ЕС. | K6: Штатный фильтр «Fara ulei de palmier» на eMAG; free-from магазины. | L6: RO | M6: EU
A7: 6 | B7: Болгария | C7: ЕС | D7: без палмово масло | E7: Нет данных | F7: =COUNTIF(Меры!$B$2:$B$26,L7)+COUNTIF(Меры!$B$2:$B$26,M7) -> 5 | G7: =COUNTIFS(Меры!$B$2:$B$26,L7,Меры!$E$2:$E$26,"Действует")+COUNTIFS(Меры!$B$2:$B$26,M7,Меры!$E$2:$E$26,"Действует") -> 3 | H7: =COUNTIFS(Меры!$B$2:$B$26,L7,Меры!$E$2:$E$26,"Принято, вступает позже")+COUNTIFS(Меры!$B$2:$B$26,M7,Меры!$E$2:$E$26,"Принято, вступает позже") -> 1 | I7: =COUNTIFS(Меры!$B$2:$B$26,L7,Меры!$E$2:$E$26,"Предложение / проект")+COUNTIFS(Меры!$B$2:$B$26,M7,Меры!$E$2:$E$26,"Предложение / проект") -> 1 | J7: Национальных норм о пальмовом масле не выявлено; действуют общие правила ЕС. | K7: Публикаций за период не найдено; заявка встречается на импорте из ЕС. | L7: BG | M7: EU
A8: 7 | B8: Эстония | C8: ЕС | D8: palmiõlita | E8: Нет данных | F8: =COUNTIF(Меры!$B$2:$B$26,L8)+COUNTIF(Меры!$B$2:$B$26,M8) -> 5 | G8: =COUNTIFS(Меры!$B$2:$B$26,L8,Меры!$E$2:$E$26,"Действует")+COUNTIFS(Меры!$B$2:$B$26,M8,Меры!$E$2:$E$26,"Действует") -> 3 | H8: =COUNTIFS(Меры!$B$2:$B$26,L8,Меры!$E$2:$E$26,"Принято, вступает позже")+COUNTIFS(Меры!$B$2:$B$26,M8,Меры!$E$2:$E$26,"Принято, вступает позже") -> 1 | I8: =COUNTIFS(Меры!$B$2:$B$26,L8,Меры!$E$2:$E$26,"Предложение / проект")+COUNTIFS(Меры!$B$2:$B$26,M8,Меры!$E$2:$E$26,"Предложение / проект") -> 1 | J8: Национальных норм о пальмовом масле не выявлено; действуют общие правила ЕС. | K8: Публикаций за период не найдено. | L8: EE | M8: EU
A9: 8 | B9: Латвия | C9: ЕС | D9: bez palmu eļļas | E9: Низкая | F9: =COUNTIF(Меры!$B$2:$B$26,L9)+COUNTIF(Меры!$B$2:$B$26,M9) -> 5 | G9: =COUNTIFS(Меры!$B$2:$B$26,L9,Меры!$E$2:$E$26,"Действует")+COUNTIFS(Меры!$B$2:$B$26,M9,Меры!$E$2:$E$26,"Действует") -> 3 | H9: =COUNTIFS(Меры!$B$2:$B$26,L9,Меры!$E$2:$E$26,"Принято, вступает позже")+COUNTIFS(Меры!$B$2:$B$26,M9,Меры!$E$2:$E$26,"Принято, вступает позже") -> 1 | I9: =COUNTIFS(Меры!$B$2:$B$26,L9,Меры!$E$2:$E$26,"Предложение / проект")+COUNTIFS(Меры!$B$2:$B$26,M9,Меры!$E$2:$E$26,"Предложение / проект") -> 1 | J9: Национальных норм о пальмовом масле не выявлено; действуют общие правила ЕС. | K9: Дискуссия о пальмовом масле в детских смесях (LSM). | L9: LV | M9: EU
A10: 9 | B10: Литва | C10: ЕС | D10: be palmių aliejaus | E10: Низкая | F10: =COUNTIF(Меры!$B$2:$B$26,L10)+COUNTIF(Меры!$B$2:$B$26,M10) -> 5 | G10: =COUNTIFS(Меры!$B$2:$B$26,L10,Меры!$E$2:$E$26,"Действует")+COUNTIFS(Меры!$B$2:$B$26,M10,Меры!$E$2:$E$26,"Действует") -> 3 | H10: =COUNTIFS(Меры!$B$2:$B$26,L10,Меры!$E$2:$E$26,"Принято, вступает позже")+COUNTIFS(Меры!$B$2:$B$26,M10,Меры!$E$2:$E$26,"Принято, вступает позже") -> 1 | I10: =COUNTIFS(Меры!$B$2:$B$26,L10,Меры!$E$2:$E$26,"Предложение / проект")+COUNTIFS(Меры!$B$2:$B$26,M10,Меры!$E$2:$E$26,"Предложение / проект") -> 1 | J10: Национальных норм о пальмовом масле не выявлено; действуют общие правила ЕС. | K10: Повестка — пальмовое масло в биотопливе, а не упаковка. | L10: LT | M10: EU
A11: 10 | B11: Хорватия | C11: ЕС | D11: bez palminog ulja | E11: Низкая | F11: =COUNTIF(Меры!$B$2:$B$26,L11)+COUNTIF(Меры!$B$2:$B$26,M11) -> 5 | G11: =COUNTIFS(Меры!$B$2:$B$26,L11,Меры!$E$2:$E$26,"Действует")+COUNTIFS(Меры!$B$2:$B$26,M11,Меры!$E$2:$E$26,"Действует") -> 3 | H11: =COUNTIFS(Меры!$B$2:$B$26,L11,Меры!$E$2:$E$26,"Принято, вступает позже")+COUNTIFS(Меры!$B$2:$B$26,M11,Меры!$E$2:$E$26,"Принято, вступает позже") -> 1 | I11: =COUNTIFS(Меры!$B$2:$B$26,L11,Меры!$E$2:$E$26,"Предложение / проект")+COUNTIFS(Меры!$B$2:$B$26,M11,Меры!$E$2:$E$26,"Предложение / проект") -> 1 | J11: Национальных норм о пальмовом масле не выявлено; действуют общие правила ЕС. | K11: В основном косметика и мыло; Lidl Hrvatska — политика RSPO, а не отказа. | L11: HR | M11: EU
A12: 11 | B12: Беларусь | C12: ЕАЭС | D12: без пальмового масла | E12: Нет данных | F12: =COUNTIF(Меры!$B$2:$B$26,L12)+COUNTIF(Меры!$B$2:$B$26,M12) -> 4 | G12: =COUNTIFS(Меры!$B$2:$B$26,L12,Меры!$E$2:$E$26,"Действует")+COUNTIFS(Меры!$B$2:$B$26,M12,Меры!$E$2:$E$26,"Действует") -> 3 | H12: =COUNTIFS(Меры!$B$2:$B$26,L12,Меры!$E$2:$E$26,"Принято, вступает позже")+COUNTIFS(Меры!$B$2:$B$26,M12,Меры!$E$2:$E$26,"Принято, вступает позже") -> 0 | I12: =COUNTIFS(Меры!$B$2:$B$26,L12,Меры!$E$2:$E$26,"Предложение / проект")+COUNTIFS(Меры!$B$2:$B$26,M12,Меры!$E$2:$E$26,"Предложение / проект") -> 1 | J12: Нормы ЕАЭС. Беларусь — инициатор обязательного указания вида растительного масла в составе. | K12: Данных о добровольной заявке за период не найдено. НАН разработала методику выявления пальмового масла в продуктах. | L12: BY | M12: EAEU
A13: 12 | B13: Молдова | C13: Вне ЕС и ЕАЭС | D13: fără ulei de palmier | E13: Низкая | F13: =COUNTIF(Меры!$B$2:$B$26,L13)+COUNTIF(Меры!$B$2:$B$26,M13) -> 1 | G13: =COUNTIFS(Меры!$B$2:$B$26,L13,Меры!$E$2:$E$26,"Действует")+COUNTIFS(Меры!$B$2:$B$26,M13,Меры!$E$2:$E$26,"Действует") -> 1 | H13: =COUNTIFS(Меры!$B$2:$B$26,L13,Меры!$E$2:$E$26,"Принято, вступает позже")+COUNTIFS(Меры!$B$2:$B$26,M13,Меры!$E$2:$E$26,"Принято, вступает позже") -> 0 | I13: =COUNTIFS(Меры!$B$2:$B$26,L13,Меры!$E$2:$E$26,"Предложение / проект")+COUNTIFS(Меры!$B$2:$B$26,M13,Меры!$E$2:$E$26,"Предложение / проект") -> 0 | J13: Усиленный контроль импортных партий пальмового масла (3-MCPD). | K13: Заявка встречается на импорте из ЕС и Румынии. | L13: MD | M13: -
... A21: 20 | B21: Армения | C21: ЕАЭС | D21: без пальмового масла | E21: Низкая | F21: =COUNTIF(Меры!$B$2:$B$26,L21)+COUNTIF(Меры!$B$2:$B$26,M21) -> 5 | G21: =COUNTIFS(Меры!$B$2:$B$26,L21,Меры!$E$2:$E$26,"Действует")+COUNTIFS(Меры!$B$2:$B$26,M21,Меры!$E$2:$E$26,"Действует") -> 4 | H21: =COUNTIFS(Меры!$B$2:$B$26,L21,Меры!$E$2:$E$26,"Принято, вступает позже")+COUNTIFS(Меры!$B$2:$B$26,M21,Меры!$E$2:$E$26,"Принято, вступает позже") -> 0 | I21: =COUNTIFS(Меры!$B$2:$B$26,L21,Меры!$E$2:$E$26,"Предложение / проект")+COUNTIFS(Меры!$B$2:$B$26,M21,Меры!$E$2:$E$26,"Предложение / проект") -> 1 | J21: Нормы ЕАЭС + надпись «содержит заменитель молочного жира» и отдельная выкладка с 27.04.2025. | K21: Заявка единичная. | L21: AM | M21: EAEU
B23: Итого норм в базе | F23: =COUNTA(Меры!$A$2:$A$26) -> 25 | G23: =COUNTIF(Меры!$E$2:$E$26,"Действует") -> 15 | H23: =COUNTIF(Меры!$E$2:$E$26,"Принято, вступает позже") -> 4 | I23: =COUNTIF(Меры!$E$2:$E$26,"Предложение / проект") -> 6
B24: Столбцы F–I считаются формулами по листу «Меры»: нормы страны + общие нормы её блока (ЕС или ЕАЭС). Столбец E — экспертная оценка по публикациям, выбирается из списка.

Sheet Меры
A1: № | B1: Код охвата | C1: Охват | D1: Тип меры | E1: Статус | F1: Дата вступления | G1: Правовой акт / источник нормы | H1: Мера | I1: Описание | J1: Measure (EN) | K1: Description (EN) | L1: Ссылка
A2: 1 | B2: EU | C2: ЕС (общие нормы) | D2: Раскрытие в составе / маркировка | E2: Действует | F2: 13.12.2014 | G2: Регламент (ЕС) № 1169/2011 (FIC) | H2: Обязательное указание вида растительного масла | I2: Рафинированные масла в составе указываются с ботаническим происхождением — «пальмовое» нельзя скрыть за «растительным жиром». Добровольная заявка «без пальмового масла» допустима, если правдива и не вводит в заблуждение. | J2: Mandatory naming of the vegetable oil | K2: Refined oils in the ingredient list must state their vegetable origin, so palm oil cannot hide behind ‘vegetable fat’. A voluntary ‘palm oil free’ claim is allowed if true and not misleading. | L2: https://eur-lex.europa.eu/eli/reg/2011/1169/oj
A3: 2 | B3: EU | C3: ЕС (общие нормы) | D3: Правила заявок | E3: Действует | F3: 28.05.2022 | G3: Директива (ЕС) 2019/2161 (Omnibus), ст. 6(2)(c) UCPD | H3: Запрет «двойного качества» | I3: Нельзя продавать под одним брендом товар заметно иного состава в разных странах ЕС без объективной причины — основание споров о замене масла на пальмовое в рецептурах для Восточной Европы. | J3: Ban on ‘dual quality’ | K3: A product marketed as identical across EU countries may not differ markedly in composition without an objective reason — the basis of disputes over palm oil replacing butter in East European recipes. | L3: https://eur-lex.europa.eu/eli/dir/2019/2161/oj
A4: 3 | B4: EU | C4: ЕС (общие нормы) | D4: Правила заявок | E4: Действует | F4: 27.09.2026 | G4: Директива (ЕС) 2024/825 (EmpCo) | H4: Запрет общих эко-заявок и самодельных эко-значков | I4: Общие экологические заявки без признанной выдающейся экологичности и собственные эко-лейблы без сертификации запрещены. «Без пальмового масла» само по себе не запрещено, но эко-обоснование («ради лесов») и самодельные значки «palm oil free» — под риском. | J4: Ban on generic green claims and self-made eco labels | K4: Generic environmental claims without recognised excellent performance and uncertified own eco labels are banned. ‘Palm oil free’ itself is not banned, but eco framing (‘to save forests’) and home-made ‘palm oil free’ badges are at risk. | L4: https://eur-lex.europa.eu/eli/dir/2024/825/oj
A5: 4 | B5: EU | C5: ЕС (общие нормы) | D5: Устойчивость (EUDR) | E5: Принято, вступает позже | F5: 30.12.2026 | G5: Регламент (ЕС) 2023/1115 (EUDR), ред. 2025/2650 | H5: Пальмовое масло только «deforestation-free» | I5: Операторы обязаны доказать, что пальмовое масло не связано с вырубкой лесов после 31.12.2020 (геолокация плантаций). Средние и крупные — с 30.12.2026, малые и микро — с 30.06.2027. | J5: Palm oil must be deforestation-free | K5: Operators must prove palm oil is not linked to deforestation after 31 Dec 2020 (plot geolocation). Medium and large firms from 30 Dec 2026, micro and small from 30 Jun 2027. | L5: https://vinciworks.com/blog/eudr-delayed-again-what-changed-what-is-now-fixed-and-what-businesses-should-do-in-2026/
A6: 5 | B6: EU | C6: ЕС (общие нормы) | D6: Устойчивость (EUDR) | E6: Предложение / проект | F6: 04.05.2026 | G6: Проект делегированного акта к EUDR | H6: Расширение EUDR на производные пальмового масла | I6: Еврокомиссия предложила включить олеохимию (жирные кислоты, их эфиры, мыло на пальмовом масле). | J6: EUDR extended to palm oil derivatives | K6: The Commission proposed adding oleochemicals (fatty acids, their esters, palm-based soap). | L6: https://blog.foodsconnected.com/7-key-takeaways-from-the-april-2026-eudr-review
A7: 6 | B7: EAEU | C7: ЕАЭС (общие нормы) | D7: Раскрытие в составе / маркировка | E7: Действует | F7: 01.07.2013 | G7: ТР ТС 022/2011 «Пищевая продукция в части её маркировки» | H7: Допускается общее название «масло растительное» | I7: Рафинированные масла можно указывать в составе как «масло (жир) растительное» без вида — главная лазейка, позволяющая не называть пальмовое масло. | J7: Generic ‘vegetable oil’ name allowed | K7: Refined oils may be listed as ‘vegetable oil (fat)’ without the species — the main loophole for not naming palm oil. | L7: https://eec.eaeunion.org/comission/department/deptexreg/tr/PischevkaMarkirovka.php
A8: 7 | B8: EAEU | C8: ЕАЭС (общие нормы) | D8: Раскрытие в составе / маркировка | E8: Предложение / проект | F8: — | G8: Изменения в ТР ТС 022/2011 (разработчик — Беларусь) | H8: Обязательное указание вида растительного масла | I8: Предложено обязать указывать вид масла в составе; Минздрав Казахстана поддержал, «Атамекен» возражал. Изменение пока не принято. | J8: Mandatory naming of the vegetable oil species | K8: Proposal to require the oil species in the ingredient list; Kazakhstan’s health ministry supported it, Atameken objected. Not adopted yet. | L8: https://nkprom.ru/news/v-tr-ts-022-2011-pishchevaya-produktsiya-v-chasti-ee-markirovki-i-tr-ts-022-2011-o-bezopasnosti-sred/
A9: 8 | B9: EAEU | C9: ЕАЭС (общие нормы) | D9: Стандарты качества | E9: Действует | F9: 22.12.2024 | G9: ТР ТС 024/2011 «Технический регламент на масложировую продукцию» (новая ред.) | H9: Обновлённые требования к масложировой продукции | I9: Новые определения спредов, топлёных смесей, переэтерифицированных жиров, понятие повторной рафинации. | J9: Updated rules for oil and fat products | K9: New definitions of spreads, blended fats, interesterified fats; concept of re-refining. | L9: https://foodsmi.com/zakonodatelstvo/izmeneniya-v-tekhreglamente-na-maslozhirovuyu-produktsiyu/
A10: 9 | B10: EAEU | C10: ЕАЭС (общие нормы) | D10: Молочка и заменители молочного жира | E10: Действует | F10: — | G10: ТР ТС 033/2013 «О безопасности молока и молочной продукции» | H10: Продукты с заменителем молочного жира — отдельная категория | I10: Продукция с растительными жирами называется «молокосодержащий продукт с заменителем молочного жира» («спред», «сырный продукт» и т. п.) и не может называться маслом или сыром. | J10: Products with milk fat substitute are a separate category | K10: Products with vegetable fats must be called ‘milk-containing product with milk fat substitute’ (spread, cheese product, etc.), not butter or cheese. | L10: —
A11: 10 | B11: UA | C11: Украина | D11: Запрет / ограничение состава | E11: Действует | F11: 11.2025 | G11: Закон України № 3947-IX від 04.09.2024 | H11: Запреты пальмового масла в молочке, детском питании и кондитерке | I11: Запрет пальмового масла в традиционных молочных продуктах; гидрогенизированных жиров — в детском питании и кондитерке (шоколад, мороженое); лимит трансжиров ≤ 2 г на 100 г жира; штрафы 45–65 минимальных зарплат. Подписан 6.11.2024, вводится в действие через год после опубликования. | J11: Palm oil bans in dairy, baby food and confectionery | K11: Bans palm oil in traditional dairy; hydrogenated fats in baby food and confectionery (chocolate, ice cream); trans fat ≤ 2 g per 100 g of fat; fines of 45–65 minimum wages. Signed 6 Nov 2024, enacted one year after publication. | L11: https://biz.ligazakon.net/news/231710_prezident-pdpisav-zakon-pro-obmezhennya-vikoristannya-palmovo-ol-u-produktakh-kharchuvannya
A12: 11 | B12: UA | C12: Украина | D12: Раскрытие в составе / маркировка | E12: Действует | F12: 11.2025 | G12: Закон України № 3947-IX | H12: Маркировка продуктов с пальмовым маслом | I12: Закон требует «чёткой и понятной» маркировки. Законопроект предусматривал надпись «містить пальмову олію»; разъяснения 2026 года указывают, что отдельного значка на лицевой стороне нет — формат требует проверки по тексту закона. | J12: Labelling of products containing palm oil | K12: The law requires ‘clear and understandable’ labelling. The bill foresaw a ‘contains palm oil’ statement; 2026 guidance says there is no separate front-of-pack mark — format to verify against the law text. | L12: https://ngu.com.ua/palmova-oliia-shkoda-sklad-doza-i-etyketka/
A13: 12 | B13: MD | C13: Молдова | D13: Импортный контроль | E13: Действует | F13: 04.09.2025 | G13: Приказ ANSA № 352 от 04.09.2025 (изм. приказом № 369) | H13: Усиленный контроль импортного пальмового масла | I13: Партии пальмового масла на границе проходят лабораторные испытания, в том числе на 3-MCPD, после выявленных превышений. | J13: Tighter control of imported palm oil | K13: Palm oil lots are lab-tested at the border, including for 3-MCPD, after exceedances were found. | L13: https://ansa.gov.md/sites/default/files/documents/Ordine/Ordin%20nr.%20369.pdf
... A26: 25 | B26: AM | C26: Армения | D26: Молочка и заменители молочного жира | E26: Действует | F26: 27.04.2025 | G26: Поправки в Кодекс РА об административных правонарушениях | H26: «Содержит заменитель молочного жира» | I26: Продукты с заменителями молочного жира выкладываются отдельно и маркируются надписью «содержит заменитель молочного жира». | J26: ‘Contains milk fat substitute’ | K26: Products with milk fat substitutes are shelved separately and labelled ‘contains milk fat substitute’. | L26: https://dairynews.today/kz/news/armenia-to-enforce-stricter-labeling-rules-for-dairy-and-meat-products.html

Sheet Справочник
A1: Регуляторная политика: маркировки и пальмовое масло
A2: Подготовлено | B2: International Marketing Agency (IMA)
A3: Данные на | B3: 23.10.2026
A4: Период обзора | B4: октябрь 2025 – октябрь 2026 (и действующие нормы прошлых лет)
A6: Статусы
A7: Действует
A8: Принято, вступает позже
A9: Предложение / проект
A11: Типы мер
A12: Раскрытие в составе / маркировка
A13: Правила заявок
A14: Запрет / ограничение состава
A15: Молочка и заменители молочного жира
A16: Импортный контроль
A17: Цифровая маркировка и прослеживаемость
A18: Налоги
... A20: Устойчивость (EUDR)
A22: Шкала использования заявки | B22: Экспертная оценка по найденным публикациям: Высокая / Средняя / Низкая / Нет / Нет данных.
A23: Ограничения | B23: Источники — открытый веб на национальных языках. Аудит полок и платные базы (Mintel GNPD, Euromonitor) не использовались. Даты без дня указаны с точностью до месяца или года; «—» — дата не установлена.
A24: Оговорка | B24: Справочный материал, не юридическая консультация. Перед решениями проверяйте текст нормы по ссылке.
