Workbook

Sheet Country summary
A1: No. | B1: Country | C1: Bloc | D1: On-pack wording | E1: Use of the “palm oil free” claim | F1: Rules total (incl. bloc) | G1: In force | H1: Apply later | I1: Proposals | J1: Rules in brief | K1: Market practice of the claim | L1: Code | M1: Bloc code
A2: 1 | B2: Poland | C2: EU | D2: bez oleju palmowego (“palm oil free”) | E2: High | F2: =COUNTIF(Rules!$B$2:$B$26,L2)+COUNTIF(Rules!$B$2:$B$26,M2) -> 5 | G2: =COUNTIFS(Rules!$B$2:$B$26,L2,Rules!$E$2:$E$26,"In force")+COUNTIFS(Rules!$B$2:$B$26,M2,Rules!$E$2:$E$26,"In force") -> 3 | H2: =COUNTIFS(Rules!$B$2:$B$26,L2,Rules!$E$2:$E$26,"Adopted, applies later")+COUNTIFS(Rules!$B$2:$B$26,M2,Rules!$E$2:$E$26,"Adopted, applies later") -> 1 | I2: =COUNTIFS(Rules!$B$2:$B$26,L2,Rules!$E$2:$E$26,"Proposal / draft")+COUNTIFS(Rules!$B$2:$B$26,M2,Rules!$E$2:$E$26,"Proposal / draft") -> 1 | J2: No national palm-specific rules; EU rules apply. | K2: Żabka: 100% of private label palm-free, supplier brands RSPO-only. Claim used on snacks, spreads, infant formula, B2B bakery margarines. | L2: PL | M2: EU
A3: 2 | B3: Czech Republic | C3: EU | D3: bez palmového oleje (“palm oil free”) | E3: High | F3: =COUNTIF(Rules!$B$2:$B$26,L3)+COUNTIF(Rules!$B$2:$B$26,M3) -> 5 | G3: =COUNTIFS(Rules!$B$2:$B$26,L3,Rules!$E$2:$E$26,"In force")+COUNTIFS(Rules!$B$2:$B$26,M3,Rules!$E$2:$E$26,"In force") -> 3 | H3: =COUNTIFS(Rules!$B$2:$B$26,L3,Rules!$E$2:$E$26,"Adopted, applies later")+COUNTIFS(Rules!$B$2:$B$26,M3,Rules!$E$2:$E$26,"Adopted, applies later") -> 1 | I3: =COUNTIFS(Rules!$B$2:$B$26,L3,Rules!$E$2:$E$26,"Proposal / draft")+COUNTIFS(Rules!$B$2:$B$26,M3,Rules!$E$2:$E$26,"Proposal / draft") -> 1 | J3: No national palm-specific rules; EU rules apply. | K3: Claim built into product names in online retail (Rohlik: Lef, Chocoland). Home of the 1 February ‘Palm Oil Free Day’. | L3: CZ | M3: EU
A4: 3 | B4: Slovakia | C4: EU | D4: bez palmového oleja (“palm oil free”) | E4: Medium | F4: =COUNTIF(Rules!$B$2:$B$26,L4)+COUNTIF(Rules!$B$2:$B$26,M4) -> 5 | G4: =COUNTIFS(Rules!$B$2:$B$26,L4,Rules!$E$2:$E$26,"In force")+COUNTIFS(Rules!$B$2:$B$26,M4,Rules!$E$2:$E$26,"In force") -> 3 | H4: =COUNTIFS(Rules!$B$2:$B$26,L4,Rules!$E$2:$E$26,"Adopted, applies later")+COUNTIFS(Rules!$B$2:$B$26,M4,Rules!$E$2:$E$26,"Adopted, applies later") -> 1 | I4: =COUNTIFS(Rules!$B$2:$B$26,L4,Rules!$E$2:$E$26,"Proposal / draft")+COUNTIFS(Rules!$B$2:$B$26,M4,Rules!$E$2:$E$26,"Proposal / draft") -> 1 | J4: No national palm-specific rules; EU rules apply, including the dual-quality ban. | K4: Local nut-spread brands; ‘dual quality’ debate (palm oil instead of butter in recipes for the East). | L4: SK | M4: EU
A5: 4 | B5: Hungary | C5: EU | D5: pálmaolaj-mentes (“palm oil free”) | E5: Low | F5: =COUNTIF(Rules!$B$2:$B$26,L5)+COUNTIF(Rules!$B$2:$B$26,M5) -> 5 | G5: =COUNTIFS(Rules!$B$2:$B$26,L5,Rules!$E$2:$E$26,"In force")+COUNTIFS(Rules!$B$2:$B$26,M5,Rules!$E$2:$E$26,"In force") -> 3 | H5: =COUNTIFS(Rules!$B$2:$B$26,L5,Rules!$E$2:$E$26,"Adopted, applies later")+COUNTIFS(Rules!$B$2:$B$26,M5,Rules!$E$2:$E$26,"Adopted, applies later") -> 1 | I5: =COUNTIFS(Rules!$B$2:$B$26,L5,Rules!$E$2:$E$26,"Proposal / draft")+COUNTIFS(Rules!$B$2:$B$26,M5,Rules!$E$2:$E$26,"Proposal / draft") -> 1 | J5: No national palm-specific rules found; EU rules apply. | K5: Free-from niche; media focus on prices and EUDR. | L5: HU | M5: EU
A6: 5 | B6: Romania | C6: EU | D6: fără ulei de palmier (“palm oil free”) | E6: Medium | F6: =COUNTIF(Rules!$B$2:$B$26,L6)+COUNTIF(Rules!$B$2:$B$26,M6) -> 5 | G6: =COUNTIFS(Rules!$B$2:$B$26,L6,Rules!$E$2:$E$26,"In force")+COUNTIFS(Rules!$B$2:$B$26,M6,Rules!$E$2:$E$26,"In force") -> 3 | H6: =COUNTIFS(Rules!$B$2:$B$26,L6,Rules!$E$2:$E$26,"Adopted, applies later")+COUNTIFS(Rules!$B$2:$B$26,M6,Rules!$E$2:$E$26,"Adopted, applies later") -> 1 | I6: =COUNTIFS(Rules!$B$2:$B$26,L6,Rules!$E$2:$E$26,"Proposal / draft")+COUNTIFS(Rules!$B$2:$B$26,M6,Rules!$E$2:$E$26,"Proposal / draft") -> 1 | J6: No national palm-specific rules found; EU rules apply. | K6: Standard ‘Fara ulei de palmier’ filter on eMAG; free-from shops. | L6: RO | M6: EU
A7: 6 | B7: Bulgaria | C7: EU | D7: без палмово масло (“palm oil free”) | E7: No data | F7: =COUNTIF(Rules!$B$2:$B$26,L7)+COUNTIF(Rules!$B$2:$B$26,M7) -> 5 | G7: =COUNTIFS(Rules!$B$2:$B$26,L7,Rules!$E$2:$E$26,"In force")+COUNTIFS(Rules!$B$2:$B$26,M7,Rules!$E$2:$E$26,"In force") -> 3 | H7: =COUNTIFS(Rules!$B$2:$B$26,L7,Rules!$E$2:$E$26,"Adopted, applies later")+COUNTIFS(Rules!$B$2:$B$26,M7,Rules!$E$2:$E$26,"Adopted, applies later") -> 1 | I7: =COUNTIFS(Rules!$B$2:$B$26,L7,Rules!$E$2:$E$26,"Proposal / draft")+COUNTIFS(Rules!$B$2:$B$26,M7,Rules!$E$2:$E$26,"Proposal / draft") -> 1 | J7: No national palm-specific rules found; EU rules apply. | K7: No publications found for the period; claim seen on EU imports. | L7: BG | M7: EU
A8: 7 | B8: Estonia | C8: EU | D8: palmiõlita (“palm oil free”) | E8: No data | F8: =COUNTIF(Rules!$B$2:$B$26,L8)+COUNTIF(Rules!$B$2:$B$26,M8) -> 5 | G8: =COUNTIFS(Rules!$B$2:$B$26,L8,Rules!$E$2:$E$26,"In force")+COUNTIFS(Rules!$B$2:$B$26,M8,Rules!$E$2:$E$26,"In force") -> 3 | H8: =COUNTIFS(Rules!$B$2:$B$26,L8,Rules!$E$2:$E$26,"Adopted, applies later")+COUNTIFS(Rules!$B$2:$B$26,M8,Rules!$E$2:$E$26,"Adopted, applies later") -> 1 | I8: =COUNTIFS(Rules!$B$2:$B$26,L8,Rules!$E$2:$E$26,"Proposal / draft")+COUNTIFS(Rules!$B$2:$B$26,M8,Rules!$E$2:$E$26,"Proposal / draft") -> 1 | J8: No national palm-specific rules found; EU rules apply. | K8: No publications found for the period. | L8: EE | M8: EU
A9: 8 | B9: Latvia | C9: EU | D9: bez palmu eļļas (“palm oil free”) | E9: Low | F9: =COUNTIF(Rules!$B$2:$B$26,L9)+COUNTIF(Rules!$B$2:$B$26,M9) -> 5 | G9: =COUNTIFS(Rules!$B$2:$B$26,L9,Rules!$E$2:$E$26,"In force")+COUNTIFS(Rules!$B$2:$B$26,M9,Rules!$E$2:$E$26,"In force") -> 3 | H9: =COUNTIFS(Rules!$B$2:$B$26,L9,Rules!$E$2:$E$26,"Adopted, applies later")+COUNTIFS(Rules!$B$2:$B$26,M9,Rules!$E$2:$E$26,"Adopted, applies later") -> 1 | I9: =COUNTIFS(Rules!$B$2:$B$26,L9,Rules!$E$2:$E$26,"Proposal / draft")+COUNTIFS(Rules!$B$2:$B$26,M9,Rules!$E$2:$E$26,"Proposal / draft") -> 1 | J9: No national palm-specific rules found; EU rules apply. | K9: Debate about palm oil in infant formula (LSM). | L9: LV | M9: EU
A10: 9 | B10: Lithuania | C10: EU | D10: be palmių aliejaus (“palm oil free”) | E10: Low | F10: =COUNTIF(Rules!$B$2:$B$26,L10)+COUNTIF(Rules!$B$2:$B$26,M10) -> 5 | G10: =COUNTIFS(Rules!$B$2:$B$26,L10,Rules!$E$2:$E$26,"In force")+COUNTIFS(Rules!$B$2:$B$26,M10,Rules!$E$2:$E$26,"In force") -> 3 | H10: =COUNTIFS(Rules!$B$2:$B$26,L10,Rules!$E$2:$E$26,"Adopted, applies later")+COUNTIFS(Rules!$B$2:$B$26,M10,Rules!$E$2:$E$26,"Adopted, applies later") -> 1 | I10: =COUNTIFS(Rules!$B$2:$B$26,L10,Rules!$E$2:$E$26,"Proposal / draft")+COUNTIFS(Rules!$B$2:$B$26,M10,Rules!$E$2:$E$26,"Proposal / draft") -> 1 | J10: No national palm-specific rules found; EU rules apply. | K10: Debate centres on palm oil in biofuel, not packaging. | L10: LT | M10: EU
A11: 10 | B11: Croatia | C11: EU | D11: bez palminog ulja (“palm oil free”) | E11: Low | F11: =COUNTIF(Rules!$B$2:$B$26,L11)+COUNTIF(Rules!$B$2:$B$26,M11) -> 5 | G11: =COUNTIFS(Rules!$B$2:$B$26,L11,Rules!$E$2:$E$26,"In force")+COUNTIFS(Rules!$B$2:$B$26,M11,Rules!$E$2:$E$26,"In force") -> 3 | H11: =COUNTIFS(Rules!$B$2:$B$26,L11,Rules!$E$2:$E$26,"Adopted, applies later")+COUNTIFS(Rules!$B$2:$B$26,M11,Rules!$E$2:$E$26,"Adopted, applies later") -> 1 | I11: =COUNTIFS(Rules!$B$2:$B$26,L11,Rules!$E$2:$E$26,"Proposal / draft")+COUNTIFS(Rules!$B$2:$B$26,M11,Rules!$E$2:$E$26,"Proposal / draft") -> 1 | J11: No national palm-specific rules found; EU rules apply. | K11: Mostly cosmetics and soap; Lidl Hrvatska follows RSPO sourcing, not avoidance. | L11: HR | M11: EU
A12: 11 | B12: Belarus | C12: EAEU | D12: без пальмового масла (“palm oil free”) | E12: No data | F12: =COUNTIF(Rules!$B$2:$B$26,L12)+COUNTIF(Rules!$B$2:$B$26,M12) -> 4 | G12: =COUNTIFS(Rules!$B$2:$B$26,L12,Rules!$E$2:$E$26,"In force")+COUNTIFS(Rules!$B$2:$B$26,M12,Rules!$E$2:$E$26,"In force") -> 3 | H12: =COUNTIFS(Rules!$B$2:$B$26,L12,Rules!$E$2:$E$26,"Adopted, applies later")+COUNTIFS(Rules!$B$2:$B$26,M12,Rules!$E$2:$E$26,"Adopted, applies later") -> 0 | I12: =COUNTIFS(Rules!$B$2:$B$26,L12,Rules!$E$2:$E$26,"Proposal / draft")+COUNTIFS(Rules!$B$2:$B$26,M12,Rules!$E$2:$E$26,"Proposal / draft") -> 1 | J12: EAEU rules. Belarus initiated the push to require the specific vegetable oil in ingredient lists. | K12: No data on voluntary claims for the period. The National Academy of Sciences developed a method to detect palm oil in food. | L12: BY | M12: EAEU
A13: 12 | B13: Moldova | C13: Outside EU and EAEU | D13: fără ulei de palmier (“palm oil free”) | E13: Low | F13: =COUNTIF(Rules!$B$2:$B$26,L13)+COUNTIF(Rules!$B$2:$B$26,M13) -> 1 | G13: =COUNTIFS(Rules!$B$2:$B$26,L13,Rules!$E$2:$E$26,"In force")+COUNTIFS(Rules!$B$2:$B$26,M13,Rules!$E$2:$E$26,"In force") -> 1 | H13: =COUNTIFS(Rules!$B$2:$B$26,L13,Rules!$E$2:$E$26,"Adopted, applies later")+COUNTIFS(Rules!$B$2:$B$26,M13,Rules!$E$2:$E$26,"Adopted, applies later") -> 0 | I13: =COUNTIFS(Rules!$B$2:$B$26,L13,Rules!$E$2:$E$26,"Proposal / draft")+COUNTIFS(Rules!$B$2:$B$26,M13,Rules!$E$2:$E$26,"Proposal / draft") -> 0 | J13: Tighter checks on imported palm oil lots (3-MCPD). | K13: Claim seen on imports from the EU and Romania. | L13: MD | M13: -
... A21: 20 | B21: Armenia | C21: EAEU | D21: без пальмового масла (“palm oil free”) | E21: Low | F21: =COUNTIF(Rules!$B$2:$B$26,L21)+COUNTIF(Rules!$B$2:$B$26,M21) -> 5 | G21: =COUNTIFS(Rules!$B$2:$B$26,L21,Rules!$E$2:$E$26,"In force")+COUNTIFS(Rules!$B$2:$B$26,M21,Rules!$E$2:$E$26,"In force") -> 4 | H21: =COUNTIFS(Rules!$B$2:$B$26,L21,Rules!$E$2:$E$26,"Adopted, applies later")+COUNTIFS(Rules!$B$2:$B$26,M21,Rules!$E$2:$E$26,"Adopted, applies later") -> 0 | I21: =COUNTIFS(Rules!$B$2:$B$26,L21,Rules!$E$2:$E$26,"Proposal / draft")+COUNTIFS(Rules!$B$2:$B$26,M21,Rules!$E$2:$E$26,"Proposal / draft") -> 1 | J21: EAEU rules + ‘contains milk fat substitute’ label and separate shelving from 27 Apr 2025. | K21: Claim is rare. | L21: AM | M21: EAEU
B23: Total rules in the database | F23: =COUNTA(Rules!$A$2:$A$26) -> 25 | G23: =COUNTIF(Rules!$E$2:$E$26,"In force") -> 15 | H23: =COUNTIF(Rules!$E$2:$E$26,"Adopted, applies later") -> 4 | I23: =COUNTIF(Rules!$E$2:$E$26,"Proposal / draft") -> 6
B24: Columns F–I are formulas over the “Rules” sheet: the country’s own rules plus the common rules of its bloc (EU or EAEU). Column E is an expert estimate based on published sources, chosen from a list.

Sheet Rules
A1: No. | B1: Scope code | C1: Scope | D1: Type of rule | E1: Status | F1: Applies from | G1: Legal act / source of the rule | H1: Rule | I1: Description | J1: Link
A2: 1 | B2: EU | C2: EU (common rules) | D2: Ingredient disclosure / labelling | E2: In force | F2: 13.12.2014 | G2: Regulation (EU) No 1169/2011 (FIC) | H2: Mandatory naming of the vegetable oil | I2: Refined oils in the ingredient list must state their vegetable origin, so palm oil cannot hide behind ‘vegetable fat’. A voluntary ‘palm oil free’ claim is allowed if true and not misleading. | J2: https://eur-lex.europa.eu/eli/reg/2011/1169/oj
A3: 2 | B3: EU | C3: EU (common rules) | D3: Claim rules | E3: In force | F3: 28.05.2022 | G3: Directive (EU) 2019/2161 (Omnibus), Art. 6(2)(c) UCPD | H3: Ban on ‘dual quality’ | I3: A product marketed as identical across EU countries may not differ markedly in composition without an objective reason — the basis of disputes over palm oil replacing butter in East European recipes. | J3: https://eur-lex.europa.eu/eli/dir/2019/2161/oj
A4: 3 | B4: EU | C4: EU (common rules) | D4: Claim rules | E4: In force | F4: 27.09.2026 | G4: Directive (EU) 2024/825 (EmpCo) | H4: Ban on generic green claims and self-made eco labels | I4: Generic environmental claims without recognised excellent performance and uncertified own eco labels are banned. ‘Palm oil free’ itself is not banned, but eco framing (‘to save forests’) and home-made ‘palm oil free’ badges are at risk. | J4: https://eur-lex.europa.eu/eli/dir/2024/825/oj
A5: 4 | B5: EU | C5: EU (common rules) | D5: Sustainability (EUDR) | E5: Adopted, applies later | F5: 30.12.2026 | G5: Regulation (EU) 2023/1115 (EUDR), as amended by 2025/2650 | H5: Palm oil must be deforestation-free | I5: Operators must prove palm oil is not linked to deforestation after 31 Dec 2020 (plot geolocation). Medium and large firms from 30 Dec 2026, micro and small from 30 Jun 2027. | J5: https://vinciworks.com/blog/eudr-delayed-again-what-changed-what-is-now-fixed-and-what-businesses-should-do-in-2026/
A6: 5 | B6: EU | C6: EU (common rules) | D6: Sustainability (EUDR) | E6: Proposal / draft | F6: 04.05.2026 | G6: Draft delegated act under EUDR | H6: EUDR extended to palm oil derivatives | I6: The Commission proposed adding oleochemicals (fatty acids, their esters, palm-based soap). | J6: https://blog.foodsconnected.com/7-key-takeaways-from-the-april-2026-eudr-review
A7: 6 | B7: EAEU | C7: EAEU (common rules) | D7: Ingredient disclosure / labelling | E7: In force | F7: 01.07.2013 | G7: TR CU 022/2011 “Food products: labelling” | H7: Generic ‘vegetable oil’ name allowed | I7: Refined oils may be listed as ‘vegetable oil (fat)’ without the species — the main loophole for not naming palm oil. | J7: https://eec.eaeunion.org/comission/department/deptexreg/tr/PischevkaMarkirovka.php
A8: 7 | B8: EAEU | C8: EAEU (common rules) | D8: Ingredient disclosure / labelling | E8: Proposal / draft | F8: — | G8: Amendments to TR CU 022/2011 (drafted by Belarus) | H8: Mandatory naming of the vegetable oil species | I8: Proposal to require the oil species in the ingredient list; Kazakhstan’s health ministry supported it, Atameken objected. Not adopted yet. | J8: https://nkprom.ru/news/v-tr-ts-022-2011-pishchevaya-produktsiya-v-chasti-ee-markirovki-i-tr-ts-022-2011-o-bezopasnosti-sred/
A9: 8 | B9: EAEU | C9: EAEU (common rules) | D9: Quality standards | E9: In force | F9: 22.12.2024 | G9: TR CU 024/2011 “Oil and fat products” (new version) | H9: Updated rules for oil and fat products | I9: New definitions of spreads, blended fats, interesterified fats; concept of re-refining. | J9: https://foodsmi.com/zakonodatelstvo/izmeneniya-v-tekhreglamente-na-maslozhirovuyu-produktsiyu/
A10: 9 | B10: EAEU | C10: EAEU (common rules) | D10: Dairy and milk fat substitutes | E10: In force | F10: — | G10: TR CU 033/2013 “Safety of milk and dairy products” | H10: Products with milk fat substitute are a separate category | I10: Products with vegetable fats must be called ‘milk-containing product with milk fat substitute’ (spread, cheese product, etc.), not butter or cheese. | J10: —
A11: 10 | B11: UA | C11: Ukraine | D11: Composition ban / restriction | E11: In force | F11: 11.2025 | G11: Law of Ukraine No. 3947-IX of 04.09.2024 | H11: Palm oil bans in dairy, baby food and confectionery | I11: Bans palm oil in traditional dairy; hydrogenated fats in baby food and confectionery (chocolate, ice cream); trans fat ≤ 2 g per 100 g of fat; fines of 45–65 minimum wages. Signed 6 Nov 2024, enacted one year after publication. | J11: https://biz.ligazakon.net/news/231710_prezident-pdpisav-zakon-pro-obmezhennya-vikoristannya-palmovo-ol-u-produktakh-kharchuvannya
A12: 11 | B12: UA | C12: Ukraine | D12: Ingredient disclosure / labelling | E12: In force | F12: 11.2025 | G12: Law of Ukraine No. 3947-IX | H12: Labelling of products containing palm oil | I12: The law requires ‘clear and understandable’ labelling. The bill foresaw a ‘contains palm oil’ statement; 2026 guidance says there is no separate front-of-pack mark — format to verify against the law text. | J12: https://ngu.com.ua/palmova-oliia-shkoda-sklad-doza-i-etyketka/
A13: 12 | B13: MD | C13: Moldova | D13: Import control | E13: In force | F13: 04.09.2025 | G13: ANSA Order No. 352 of 04.09.2025 (amended by Order No. 369) | H13: Tighter control of imported palm oil | I13: Palm oil lots are lab-tested at the border, including for 3-MCPD, after exceedances were found. | J13: https://ansa.gov.md/sites/default/files/documents/Ordine/Ordin%20nr.%20369.pdf
... A26: 25 | B26: AM | C26: Armenia | D26: Dairy and milk fat substitutes | E26: In force | F26: 27.04.2025 | G26: Amendments to Armenia’s Code of Administrative Offences | H26: ‘Contains milk fat substitute’ | I26: Products with milk fat substitutes are shelved separately and labelled ‘contains milk fat substitute’. | J26: https://dairynews.today/kz/news/armenia-to-enforce-stricter-labeling-rules-for-dairy-and-meat-products.html

Sheet Reference
A1: Regulatory policy: labelling and palm oil
A2: Prepared by | B2: International Marketing Agency (IMA)
A3: Data as of | B3: 23.10.2026
A4: Review period | B4: October 2025 – October 2026 (plus earlier rules still in force)
A6: Statuses
A7: In force
A8: Adopted, applies later
A9: Proposal / draft
A11: Types of rules
A12: Ingredient disclosure / labelling
A13: Claim rules
A14: Composition ban / restriction
A15: Dairy and milk fat substitutes
A16: Import control
A17: Digital marking and traceability
A18: Taxes
... A20: Sustainability (EUDR)
A22: Claim-use scale | B22: Expert estimate based on published sources: High / Medium / Low / None / No data.
A23: Limitations | B23: Sources: the open web in national languages. Shelf audits and paid databases (Mintel GNPD, Euromonitor) were not used. Dates without a day are given to the month or year; “—” means no date has been set.
A24: Disclaimer | B24: Reference material, not legal advice. Check the text of the rule via the link before making decisions.
